thorpy/__init__.py
thorpy/canonical.py
thorpy/elements.py
thorpy/gametools.py
thorpy/graphics.py
thorpy/loops.py
thorpy/monitoring.py
thorpy/parameters.py
thorpy/py.typed
thorpy/setup.py
thorpy/shadows.py
thorpy/sorting.py
thorpy/sound.py
thorpy/styles.py
thorpy/themes.py
thorpy/thorpytypehints.py
thorpy/data/bck.jpg
thorpy/data/check.png
thorpy/data/coin.png
thorpy/data/coin_32.png
thorpy/data/explosion.gif
thorpy/data/heart_empty_16.png
thorpy/data/heart_empty_32.png
thorpy/data/heart_full_16.png
thorpy/data/heart_full_32.png
thorpy/data/my_img.png
thorpy/data/star_empty_16.png
thorpy/data/star_empty_32.png
thorpy/data/star_full_16.png
thorpy/data/star_full_32.png
thorpy/examples/__init__.py
thorpy/examples/_example_alert.py
thorpy/examples/_example_alert2.py
thorpy/examples/_example_anim_move.py
thorpy/examples/_example_animatedgif.py
thorpy/examples/_example_box.py
thorpy/examples/_example_button_helloworld.py
thorpy/examples/_example_color_gradient.py
thorpy/examples/_example_colorpicker.py
thorpy/examples/_example_colorpicker2.py
thorpy/examples/_example_colorpicker_fine_tuning.py
thorpy/examples/_example_constrained_sliders.py
thorpy/examples/_example_create_style.py
thorpy/examples/_example_create_style2.py
thorpy/examples/_example_custom_theme.py
thorpy/examples/_example_dashed_line.py
thorpy/examples/_example_discrete_lifebar.py
thorpy/examples/_example_discrete_lifebar_fine_tuned.py
thorpy/examples/_example_dropdownlist.py
thorpy/examples/_example_events.py
thorpy/examples/_example_filebrowser.py
thorpy/examples/_example_fx_light_emitting_image.py
thorpy/examples/_example_fx_lights.py
thorpy/examples/_example_fx_sine_deformation.py
thorpy/examples/_example_get_value_from_elements.py
thorpy/examples/_example_grouping.py
thorpy/examples/_example_grouping_without_sorting.py
thorpy/examples/_example_groups_of_groups.py
thorpy/examples/_example_guess_the_number.py
thorpy/examples/_example_helper.py
thorpy/examples/_example_heterogeneous_texts.py
thorpy-2.1.13.dist-info/METADATA
thorpy-2.1.13.dist-info/WHEEL
thorpy-2.1.13.dist-info/top_level.txt
thorpy-2.1.13.dist-info/RECORD
