Metadata-Version: 2.4
Name: thorpy
Version: 2.1.13
Summary: GUI library for pygame
Home-page: http://www.thorpy.org/
Author: Yann Thorimbert
Author-email: yann.thorimbert@gmail.com
License: MIT
Keywords: pygame,gui,menus,buttons,widgets,user interface,toolkit
Dynamic: author
Dynamic: author-email
Dynamic: description
Dynamic: description-content-type
Dynamic: home-page
Dynamic: keywords
Dynamic: license
Dynamic: summary
